azure/mgmt/sitemanager/__init__.py
azure/mgmt/sitemanager/_client.py
azure/mgmt/sitemanager/_configuration.py
azure/mgmt/sitemanager/_patch.py
azure/mgmt/sitemanager/_validation.py
azure/mgmt/sitemanager/_version.py
azure/mgmt/sitemanager/py.typed
azure/mgmt/sitemanager/_utils/__init__.py
azure/mgmt/sitemanager/_utils/model_base.py
azure/mgmt/sitemanager/_utils/serialization.py
azure/mgmt/sitemanager/aio/__init__.py
azure/mgmt/sitemanager/aio/_client.py
azure/mgmt/sitemanager/aio/_configuration.py
azure/mgmt/sitemanager/aio/_patch.py
azure/mgmt/sitemanager/aio/operations/__init__.py
azure/mgmt/sitemanager/aio/operations/_operations.py
azure/mgmt/sitemanager/aio/operations/_patch.py
azure/mgmt/sitemanager/models/__init__.py
azure/mgmt/sitemanager/models/_enums.py
azure/mgmt/sitemanager/models/_models.py
azure/mgmt/sitemanager/models/_patch.py
azure/mgmt/sitemanager/operations/__init__.py
azure/mgmt/sitemanager/operations/_operations.py
azure/mgmt/sitemanager/operations/_patch.py
azure_mgmt_sitemanager-1.0.1.dist-info/licenses/LICENSE
azure_mgmt_sitemanager-1.0.1.dist-info/METADATA
azure_mgmt_sitemanager-1.0.1.dist-info/WHEEL
azure_mgmt_sitemanager-1.0.1.dist-info/top_level.txt
azure_mgmt_sitemanager-1.0.1.dist-info/RECORD
